setup.py
Dingrobot.egg-info/PKG-INFO
Dingrobot.egg-info/SOURCES.txt
Dingrobot.egg-info/dependency_links.txt
Dingrobot.egg-info/requires.txt
Dingrobot.egg-info/top_level.txt
dingrobot/__init__.py
dingrobot/fastload.py
dingrobot/robot.py