Metadata-Version: 1.0
Name: Dingrobot
Version: 4.0
Summary: Dingrobot control
Home-page: UNKNOWN
Author: WangZiPeng
Author-email: 3357223099@qq.com
License: UNKNOWN
Platform: any
